clangd/__init__.py
clangd/data/bin/clangd
clangd/data/lib/clang/21/include/__clang_cuda_builtin_vars.h
clangd/data/lib/clang/21/include/__clang_cuda_cmath.h
clangd/data/lib/clang/21/include/__clang_cuda_complex_builtins.h
clangd/data/lib/clang/21/include/__clang_cuda_device_functions.h
clangd/data/lib/clang/21/include/__clang_cuda_intrinsics.h
clangd/data/lib/clang/21/include/__clang_cuda_libdevice_declares.h
clangd/data/lib/clang/21/include/__clang_cuda_math.h
clangd/data/lib/clang/21/include/__clang_cuda_math_forward_declares.h
clangd/data/lib/clang/21/include/__clang_cuda_runtime_wrapper.h
clangd/data/lib/clang/21/include/__clang_cuda_texture_intrinsics.h
clangd/data/lib/clang/21/include/__clang_hip_cmath.h
clangd/data/lib/clang/21/include/__clang_hip_libdevice_declares.h
clangd/data/lib/clang/21/include/__clang_hip_math.h
clangd/data/lib/clang/21/include/__clang_hip_runtime_wrapper.h
clangd/data/lib/clang/21/include/__clang_hip_stdlib.h
clangd/data/lib/clang/21/include/__clang_spirv_builtins.h
clangd/data/lib/clang/21/include/__stdarg___gnuc_va_list.h
clangd/data/lib/clang/21/include/__stdarg___va_copy.h
clangd/data/lib/clang/21/include/__stdarg_header_macro.h
clangd/data/lib/clang/21/include/__stdarg_va_arg.h
clangd/data/lib/clang/21/include/__stdarg_va_copy.h
clangd/data/lib/clang/21/include/__stdarg_va_list.h
clangd/data/lib/clang/21/include/__stddef_header_macro.h
clangd/data/lib/clang/21/include/__stddef_max_align_t.h
clangd/data/lib/clang/21/include/__stddef_null.h
clangd/data/lib/clang/21/include/__stddef_nullptr_t.h
clangd/data/lib/clang/21/include/__stddef_offsetof.h
clangd/data/lib/clang/21/include/__stddef_ptrdiff_t.h
clangd/data/lib/clang/21/include/__stddef_rsize_t.h
clangd/data/lib/clang/21/include/__stddef_size_t.h
clangd/data/lib/clang/21/include/__stddef_unreachable.h
clangd/data/lib/clang/21/include/__stddef_wchar_t.h
clangd/data/lib/clang/21/include/__stddef_wint_t.h
clangd-21.1.6.dist-info/METADATA
clangd-21.1.6.dist-info/WHEEL
clangd-21.1.6.dist-info/entry_points.txt
clangd-21.1.6.dist-info/RECORD
clangd-21.1.6.dist-info/licenses/LICENSE.md
clangd-21.1.6.dist-info/sboms/auditwheel.cdx.json
