Metadata-Version: 2.4
Name: clangd
Version: 21.1.6
Summary: binaries for clangd, a clang-based C++ language server (LSP)
Keywords: clangd,llvm,clang,lsp,cpp,c
Author: LLVM team, Dan Ilan
Maintainer: Dan Ilan
License-Expression: Apache-2.0 WITH LLVM-exception
Classifier: Environment :: No Input/Output (Daemon)
Classifier: Intended Audience :: Developers
Classifier: Operating System :: OS Independent
Classifier: Programming Language :: C
Classifier: Programming Language :: C++
Classifier: Topic :: Software Development
Project-URL: Documentation, https://clangd.llvm.org/
Project-URL: Source, https://github.com/jmpfar/clangd-wheel
